mykit/__init__.py
mykit/__main__.py
mykit/app/__init__.py
mykit/app/arrow.py
mykit/app/button.py
mykit/app/label.py
mykit/app/slider.py
mykit/app/architecture/eventdriven.py
mykit/app/complex/biplot.py
mykit/app/complex/plot.py
mykit/ghactions/eLog.py
mykit/ghactions/set_output.py
mykit/kit/color.py
mykit/kit/ffmpeg.py
mykit/kit/math.py
mykit/kit/noise.py
mykit/kit/pLog.py
mykit/kit/path.py
mykit/kit/stream_capture.py
mykit/kit/text.py
mykit/kit/time.py
mykit/kit/utils.py
mykit/kit/fast_visualizations/static/plot.py
mykit/kit/keycrate/__init__.py
mykit/kit/neuralnet/dense.py
mykit/kit/neuralnet/genetic.py
mykit/rec/__init__.py
mykit/web/__init__.py
mykit-9.1.0.dist-info/LICENSE
mykit-9.1.0.dist-info/METADATA
mykit-9.1.0.dist-info/WHEEL
mykit-9.1.0.dist-info/entry_points.txt
mykit-9.1.0.dist-info/top_level.txt
mykit-9.1.0.dist-info/RECORD
