Metadata-Version: 2.1
Name: mykit
Version: 9.1.0
Summary: Python utility library
Home-page: https://nvfp.github.io/mykit
Author: Nicholas Valentinus
Author-email: nvfastplease@gmail.com
License: MIT
Project-URL: Documentation, https://nvfp.github.io/mykit/docs
Project-URL: Report bugs, https://github.com/nvfp/mykit/issues
Project-URL: Repository, https://github.com/nvfp/mykit
Project-URL: Changelog, https://nvfp.github.io/mykit/changelog
Keywords: python,toolkit,mykit
Classifier: License :: OSI Approved :: MIT License
Classifier: Natural Language :: English
Classifier: Operating System :: OS Independent
Classifier: Programming Language :: Python
Classifier: Topic :: Scientific/Engineering
Requires-Python: >=3.8
License-File: LICENSE
Requires-Dist: numba >=0.55.2
Requires-Dist: numpy >=1.22.4
